mblogutil/__init__.py
mblogutil/config.toml
mblogutil/logger.py
mblogutil-1.0.8.dist-info/LICENSE
mblogutil-1.0.8.dist-info/METADATA
mblogutil-1.0.8.dist-info/WHEEL
mblogutil-1.0.8.dist-info/top_level.txt
mblogutil-1.0.8.dist-info/RECORD
