Metadata-Version: 2.1
Name: mblogutil
Version: 1.0.8
Summary: Simple log utility for my own projects
Author-email: Bryce Jenkins <bryce@durish.xyz>
License: MIT License
Project-URL: Homepage, https://github.com/MegaBros-Games/mblogutil
Keywords: log,logging,logger
Classifier: License :: OSI Approved :: MIT License
Classifier: Programming Language :: Python
Classifier: Programming Language :: Python :: 3
Requires-Python: >=3.9
License-File: LICENSE
Requires-Dist: tomli; python_version < "3.11"
Provides-Extra: dev
Requires-Dist: black; extra == "dev"
Requires-Dist: bumpver; extra == "dev"
Requires-Dist: isort; extra == "dev"
Requires-Dist: pip-tools; extra == "dev"
Requires-Dist: pytest; extra == "dev"
